down_notifier/__init__.py
down_notifier/__main__.py
down_notifier/channel/__init__.py
down_notifier/channel/base.py
down_notifier/channel/telegram.py
down_notifier/checker.py
down_notifier/parser.py
down_notifier/site.py
down_notifier-0.1.1.dist-info/LICENSE
down_notifier-0.1.1.dist-info/WHEEL
down_notifier-0.1.1.dist-info/METADATA
down_notifier-0.1.1.dist-info/RECORD
