Metadata-Version: 2.1
Name: down-notifier
Version: 0.1.1
Summary: Send notification when your website is down.
Home-page: https://github.com/pegov/down-notifier
License: MIT
Author: pegov
Requires-Python: >=3.7,<4.0
Classifier: License :: OSI Approved :: MIT License
Classifier: Programming Language :: Python :: 3
Classifier: Programming Language :: Python :: 3.7
Classifier: Programming Language :: Python :: 3.8
Classifier: Programming Language :: Python :: 3.9
Requires-Dist: aiogram (>=2.14.3)
Requires-Dist: aiohttp (>=3.7.4)
Project-URL: Repository, https://github.com/pegov/down-notifier
